[
  {
    "latitude": 50.4680255,
    "longitude": 11.5318001,
    "total_area_sqm": 0.0,
    "capacity_mw": 0.0,
    "capacity_w": 0.0,
    "raw_output": "{\n  \"latitude\": 50.4680255,\n  \"longitude\": 11.5318001,\n  \"total_area_sqm\": 150000,\n  \"capacity_mw\": 390,\n  \"capacity_w\": 390000000,\n  \"industrial_area_name\": null,\n  \"has_plots_for_sale\": false,\n  \"plot_sizes_sqm\": [150000],\n  \"land_cost_eur\": 6750000,\n  \"infrastructure_cost_eur\": 2872500000,\n  \"power_cost_annual_eur\": 819936000,\n  \"cooling_cost_annual_eur\": 1755000,\n  \"total_capital_eur\": 288 -0,\n  \"total_annual_opex_eur\": 821691000\n}",
    "industrial_area_name": "Unknown"
  },
  {
    "latitude": 50.3502492,
    "longitude": 13.8240442,
    "total_area_sqm": 55000.0,
    "capacity_mw": 143.0,
    "capacity_w": 143000000.0,
    "industrial_area_name": "Unknown",
    "has_plots_for_sale": false,
    "plot_sizes_sqm": [],
    "land_cost_eur": 1540000.0,
    "infrastructure_cost_eur": 454300000.0,
    "power_cost_annual_eur": 187902000.0,
    "cooling_cost_annual_eur": 35035000.0,
    "total_capital_eur": 455840000.0,
    "total_annual_opex_eur": 222937000.0
  },
  {
    "latitude": 48.1354442,
    "longitude": 9.4773832,
    "total_area_sqm": 90000,
    "capacity_mw": 234.0,
    "capacity_w": 234000000.0,
    "industrial_area_name": "Unknown",
    "has_plots_for_sale": false,
    "plot_sizes_sqm": [],
    "land_cost_eur": 36000000.0,
    "infrastructure_cost_eur": 279000000.0,
    "power_cost_annual_eur": 0.0,
    "cooling_cost_annual_eur": 936000.0,
    "total_capital_eur": 315000000.0,
    "total_annual_opex_eur": 936000.0
  },
  {
    "latitude": 48.0076533,
    "longitude": 13.5916144,
    "total_area_sqm": 250000,
    "capacity_mw": 650,
    "capacity_w": 650000000,
    "industrial_area_name": "Unknown",
    "has_plots_for_sale": false,
    "plot_sizes_sqm": [],
    "land_cost_eur": 45000000,
    "infrastructure_cost_eur": 4137500000,
    "power_cost_annual_eur": 1954180800000,
    "cooling_cost_annual_eur": 32643000,
    "total_capital_eur": 4182500000,
    "total_annual_opex_eur": 1986824103000
  },
  {
    "latitude": 52.9750919,
    "longitude": 6.3013781,
    "total_area_sqm": 200000.0,
    "capacity_mw": 520.0,
    "capacity_w": 520000000.0,
    "industrial_area_name": "Ecomunitypark",
    "has_plots_for_sale": true,
    "plot_sizes_sqm": [
      92903.0,
      46452.0,
      23226.0
    ],
    "land_cost_eur": 24000000.0,
    "infrastructure_cost_eur": 1410000000.0,
    "power_cost_annual_eur": 0.0,
    "cooling_cost_annual_eur": 331760000.0,
    "total_capital_eur": 1434000000.0,
    "total_annual_opex_eur": 331760000.0
  },
  {
    "latitude": 52.1780446,
    "longitude": 12.9274304,
    "total_area_sqm": 80000,
    "capacity_mw": 208.0,
    "capacity_w": 208000000,
    "industrial_area_name": "Inspektionszugang Erdgasspeicher",
    "has_plots_for_sale": false,
    "plot_sizes_sqm": [],
    "land_cost_eur": 12080000.0,
    "infrastructure_cost_eur": 1552000000.0,
    "power_cost_annual_eur": 0.0,
    "cooling_cost_annual_eur": 122850.0,
    "total_capital_eur": 1564080000.0,
    "total_annual_opex_eur": 122850.0
  },
  {
    "latitude": 47.5086622,
    "longitude": 10.3029435,
    "total_area_sqm": 50000,
    "capacity_mw": 130.0,
    "capacity_w": 130000000.0,
    "industrial_area_name": "Unknown",
    "has_plots_for_sale": false,
    "plot_sizes_sqm": [],
    "land_cost_eur": 19000000.0,
    "infrastructure_cost_eur": 591000000.0,
    "power_cost_annual_eur": 0.0,
    "cooling_cost_annual_eur": 5355.0,
    "total_capital_eur": 610000000.0,
    "total_annual_opex_eur": 5355.0
  },
  {
    "latitude": 47.9948677,
    "longitude": 13.5971943,
    "total_area_sqm": 20000,
    "capacity_mw": 52.0,
    "capacity_w": 52000000.0,
    "industrial_area_name": "Unknown",
    "has_plots_for_sale": false,
    "plot_sizes_sqm": [],
    "land_cost_eur": 70000000.0,
    "infrastructure_cost_eur": 72000000.0,
    "power_cost_annual_eur": 0.0,
    "cooling_cost_annual_eur": 65520000.0,
    "total_capital_eur": 142000000.0,
    "total_annual_opex_eur": 65520000.0
  },
  {
    "latitude": 49.7792977,
    "longitude": 10.836393,
    "total_area_sqm": 50000.0,
    "capacity_mw": 130.0,
    "capacity_w": 130000000.0,
    "industrial_area_name": "Wiesneth Mühle",
    "has_plots_for_sale": true,
    "plot_sizes_sqm": [
      50000.0
    ],
    "land_cost_eur": 35000000.0,
    "infrastructure_cost_eur": 841500000.0,
    "power_cost_annual_eur": 390000000.0,
    "cooling_cost_annual_eur": 6337500.0,
    "total_capital_eur": 876500000.0,
    "total_annual_opex_eur": 396337500.0
  },
  {
    "latitude": 50.350565,
    "longitude": 13.8191166,
    "total_area_sqm": 50000.0,
    "capacity_mw": 130.0,
    "capacity_w": 130000000.0,
    "industrial_area_name": "Unknown",
    "has_plots_for_sale": false,
    "plot_sizes_sqm": [
      50000.0
    ],
    "land_cost_eur": 4500000.0,
    "infrastructure_cost_eur": 498500000.0,
    "power_cost_annual_eur": 0.0,
    "cooling_cost_annual_eur": 4647500.0,
    "total_capital_eur": 502500000.0,
    "total_annual_opex_eur": 4647500.0
  }
]